textgrid/__init__.py
textgrid/exceptions.py
textgrid/textgrid.py
TextGrid-1.5.dist-info/AUTHORS
TextGrid-1.5.dist-info/LICENSE
TextGrid-1.5.dist-info/METADATA
TextGrid-1.5.dist-info/WHEEL
TextGrid-1.5.dist-info/top_level.txt
TextGrid-1.5.dist-info/RECORD
