Metadata-Version: 2.1
Name: TextGrid
Version: 1.5
Summary: Praat TextGrid manipulation.
Home-page: UNKNOWN
Author: Kyle Gorman et al.
Author-email: kylebgorman@gmail.com
License: UNKNOWN
Platform: UNKNOWN
